{
    "map": {
        "url": "/img/gatech_map.svg",
        "height": 2906
    },
    "general_schedule": [
        {
            "date": "Thursday June 29th, 2023",
            "events": [
                {
                    "start": "10:00 AM",
                    "end": "7:00 PM",
                    "title": "Registration",
                    "location": "Hallway"
                },
                {
                    "start": "10:00 AM",
                    "end": "7:00 PM",
                    "title": "Expo",
                    "location": "Conference A"
                },
                {
                    "start": "12:00 PM",
                    "end": "1:00 PM",
                    "title": "Kickoff & Demo Jam",
                    "location": "Salon III & IV"
                },
                {
                    "start": "1:00 PM",
                    "end": "2:00 PM",
                    "title": "Lunch",
                    "location": ""
                },
                {
                    "title": "Hands-on Training Session #1",
                    "location": "Breakout Rooms",
                    "slot": "hotslot1"
                },
                {
                    "title": "Hands-on Training Session #2",
                    "location": "Breakout Rooms",
                    "slot": "hotslot2"
                },
                {
                    "start": "5:00 PM",
                    "end": "7:00 PM",
                    "title": "Networking Reception",
                    "location": "Expo Area"
                }
            ]
        },
        {
            "date": "Friday June 30th, 2023",
            "events": [
                {
                    "start": "7:00 AM",
                    "end": "12:30 PM",
                    "title": "Registration",
                    "location": "Hallway"
                },
                {
                    "start": "7:00 AM",
                    "end": "8:30 AM",
                    "title": "Breakfast",
                    "location": ""
                },
                {
                    "start": "8:00 AM",
                    "end": "3:00 PM",
                    "title": "Expo",
                    "location": "Conference A"
                },
                {
                    "start": "8:30 AM",
                    "end": "9:30 AM",
                    "title": "Opening Keynote",
                    "location": "Salon III & IV",
                    "anchor": "keynote"
                },
                {
                    "title": "Breakout Session #1",
                    "location": "Breakout Rooms",
                    "slot": "slot1"
                },
                {
                    "title": "Breakout Session #2",
                    "location": "Breakout Rooms",
                    "slot": "slot2"
                },
                {
                    "start": "11:45 AM",
                    "end": "1:00 PM",
                    "title": "Demo Jam",
                    "location": "Salon III & IV"
                },
                {
                    "start": "1:00 PM",
                    "end": "2:00 PM",
                    "title": "Lunch",
                    "location": ""
                },
                {
                    "title": "Breakout Session #3",
                    "location": "Breakout Rooms",
                    "slot": "slot3"
                },
                {
                    "title": "Breakout Session #4",
                    "location": "Breakout Rooms",
                    "slot": "slot4"
                },
                {
                    "title": "Breakout Session #5",
                    "location": "Breakout Rooms",
                    "slot": "slot5"
                },
                {
                    "start": "4:35 PM",
                    "end": "5:15 PM",
                    "title": "Closing",
                    "location": "Salon III & IV"
                }
            ]
        }
    ]
}